blockapiwrapper/__init__.py
blockapiwrapper/__main__.py
blockapiwrapper/base.py
blockdataapis-1.0.2.dist-info/LICENSE
blockdataapis-1.0.2.dist-info/METADATA
blockdataapis-1.0.2.dist-info/WHEEL
blockdataapis-1.0.2.dist-info/entry_points.txt
blockdataapis-1.0.2.dist-info/top_level.txt
blockdataapis-1.0.2.dist-info/RECORD
