Metadata-Version: 2.1
Name: blockdataapis
Version: 1.0.2
Summary: Reads blockchain data from apis gotten from exchanges, NFT Marketplaces, explorers etc
Author-email: Aminat Amusa <minaomobonike@gmail.com>
License: The MIT License (MIT)
Project-URL: Homepage, https://github.com/minat-hub/Blockdataapis
Keywords: Blockchain,Cryptocurrencies,NFTs
Classifier: License :: OSI Approved :: MIT License
Classifier: Programming Language :: Python
Classifier: Programming Language :: Python :: 3
Requires-Python: >=3.9
License-File: LICENSE
Requires-Dist: requests (>=2.28.1)
Requires-Dist: python-decouple (>=3.6)
Requires-Dist: pytest (>=3.0.3)
Provides-Extra: dev
Requires-Dist: black ; extra == 'dev'
Requires-Dist: bumpver ; extra == 'dev'
Requires-Dist: isort ; extra == 'dev'
Requires-Dist: pip-tools ; extra == 'dev'
Requires-Dist: pandas ; extra == 'dev'
